internshala_bot/__init__.py
internshala_bot/__main__.py
internshala_bot/assignment_helper.py
internshala_bot/chat_gpt.py
internshala_bot/generate_report.py
internshala_bot/main.py
internshala_bot/resume_handler.py
internshala_bot-0.1.1.dist-info/LICENSE
internshala_bot-0.1.1.dist-info/METADATA
internshala_bot-0.1.1.dist-info/WHEEL
internshala_bot-0.1.1.dist-info/entry_points.txt
internshala_bot-0.1.1.dist-info/top_level.txt
internshala_bot-0.1.1.dist-info/RECORD
