Metadata-Version: 2.1
Name: internshala-bot
Version: 0.1.1
Summary: Package to automate internship application process on Internshala using ChatGPT.
Home-page: https://github.com/Eviltr0N/internshala-bot
Author: Mayank Lodhi
Author-email: 
License: Apache-2.0
Project-URL: Bug Reports, https://github.com/Eviltr0N/internshala-bot/issues
Project-URL: Source Code, https://github.com/Eviltr0N/internshala-bot/
Project-URL: Youtube, https://youtu.be/l0Pgz9-QB_E
Classifier: Intended Audience :: Developers
Classifier: License :: OSI Approved :: Apache Software License
Classifier: Operating System :: OS Independent
License-File: LICENSE
Requires-Dist: undetected-playwright-patch ==1.40.0-1700587210000
Requires-Dist: rich ==13.7.1
Requires-Dist: argparse
Requires-Dist: requests
Requires-Dist: requests-html
Requires-Dist: pandas
Requires-Dist: lxml-html-clean
